L1.2/equality_comparator.v

module equality_comparator (
    input [3:0] A,    
    input [3:0] B,    
    output equal      
);

    
    wire eq0, eq1, eq2, eq3;
     assign eq0 = ~(A[0] ^ B[0]);  
     assign eq1 = ~(A[1] ^ B[1]);  
     assign eq2 = ~(A[2] ^ B[2]);  
     assign eq3 = ~(A[3] ^ B[3]);  
     assign equal = eq0 & eq1 & eq2 & eq3;  

endmodule

L1.2/tb_equality_comparator.v

`timescale 1ns/1ps
`include "equality_comparator.v"  

module equality_comparator_tb;

    
    reg [3:0] A;      
    reg [3:0] B;      
    wire equal;       
    
    
    equality_comparator uut (
        .A(A),
        .B(B),
        .equal(equal)
    );
    
    
    initial begin
        
        $dumpfile("equality_comparator.vcd");
        $dumpvars(0, equality_comparator_tb);
        
        
        for (integer i = 0; i < 16; i = i + 1) begin
            for (integer j = 0; j < 16; j = j + 1) begin
                A = i[3:0];
                B = j[3:0];
                #5;
            end
        end
        
        
    end
    
    
endmodule

L1.2/equality_comparator.vcd
$date
	Thu Jul 31 13:33:06 2025
$end
$version
	Icarus Verilog
$end
$timescale
	1ps
$end
$scope module equality_comparator_tb $end
$var wire 1 ! equal $end
$var reg 4 " A [3:0] $end
$var reg 4 # B [3:0] $end
$scope module uut $end
$var wire 4 $ A [3:0] $end
$var wire 4 % B [3:0] $end
$var wire 1 ! equal $end
$upscope $end
$scope begin $ivl_for_loop0 $end
$var integer 32 & i [31:0] $end
$scope begin $ivl_for_loop1 $end
$var integer 32 ' j [31:0] $end
$upscope $end
$upscope $end
$upscope $end
$enddefinitions $end
#0
$dumpvars
b0 '
b0 &
b0 %
b0 $
b0 #
b0 "
1!
$end
#5000
0!
b1 #
b1 %
b1 '
#10000
b10 #
b10 %
b10 '
#15000
b11 #
b11 %
b11 '
#20000
b100 #
b100 %
b100 '
#25000
b101 #
b101 %
b101 '
#30000
b110 #
b110 %
b110 '
#35000
b111 #
b111 %
b111 '
#40000
b1000 #
b1000 %
b1000 '
#45000
b1001 #
b1001 %
b1001 '
#50000
b1010 #
b1010 %
b1010 '
#55000
b1011 #
b1011 %
b1011 '
#60000
b1100 #
b1100 %
b1100 '
#65000
b1101 #
b1101 %
b1101 '
#70000
b1110 #
b1110 %
b1110 '
#75000
b1111 #
b1111 %
b1111 '
#80000
b0 #
b0 %
b1 "
b1 $
b1 &
b0 '
#85000
1!
b1 #
b1 %
b1 '
#90000
0!
b10 #
b10 %
b10 '
#95000
b11 #
b11 %
b11 '
#100000
b100 #
b100 %
b100 '
#105000
b101 #
b101 %
b101 '
#110000
b110 #
b110 %
b110 '
#115000
b111 #
b111 %
b111 '
#120000
b1000 #
b1000 %
b1000 '
#125000
b1001 #
b1001 %
b1001 '
#130000
b1010 #
b1010 %
b1010 '
#135000
b1011 #
b1011 %
b1011 '
#140000
b1100 #
b1100 %
b1100 '
#145000
b1101 #
b1101 %
b1101 '
#150000
b1110 #
b1110 %
b1110 '
#155000
b1111 #
b1111 %
b1111 '
#160000
b0 #
b0 %
b10 "
b10 $
b10 &
b0 '
#165000
b1 #
b1 %
b1 '
#170000
1!
b10 #
b10 %
b10 '
#175000
0!
b11 #
b11 %
b11 '
#180000
b100 #
b100 %
b100 '
#185000
b101 #
b101 %
b101 '
#190000
b110 #
b110 %
b110 '
#195000
b111 #
b111 %
b111 '
#200000
b1000 #
b1000 %
b1000 '
#205000
b1001 #
b1001 %
b1001 '
#210000
b1010 #
b1010 %
b1010 '
#215000
b1011 #
b1011 %
b1011 '
#220000
b1100 #
b1100 %
b1100 '
#225000
b1101 #
b1101 %
b1101 '
#230000
b1110 #
b1110 %
b1110 '
#235000
b1111 #
b1111 %
b1111 '
#240000
b0 #
b0 %
b11 "
b11 $
b11 &
b0 '
#245000
b1 #
b1 %
b1 '
#250000
b10 #
b10 %
b10 '
#255000
1!
b11 #
b11 %
b11 '
#260000
0!
b100 #
b100 %
b100 '
#265000
b101 #
b101 %
b101 '
#270000
b110 #
b110 %
b110 '
#275000
b111 #
b111 %
b111 '
#280000
b1000 #
b1000 %
b1000 '
#285000
b1001 #
b1001 %
b1001 '
#290000
b1010 #
b1010 %
b1010 '
#295000
b1011 #
b1011 %
b1011 '
#300000
b1100 #
b1100 %
b1100 '
#305000
b1101 #
b1101 %
b1101 '
#310000
b1110 #
b1110 %
b1110 '
#315000
b1111 #
b1111 %
b1111 '
#320000
b0 #
b0 %
b100 "
b100 $
b100 &
b0 '
#325000
b1 #
b1 %
b1 '
#330000
b10 #
b10 %
b10 '
#335000
b11 #
b11 %
b11 '
#340000
1!
b100 #
b100 %
b100 '
#345000
0!
b101 #
b101 %
b101 '
#350000
b110 #
b110 %
b110 '
#355000
b111 #
b111 %
b111 '
#360000
b1000 #
b1000 %
b1000 '
#365000
b1001 #
b1001 %
b1001 '
#370000
b1010 #
b1010 %
b1010 '
#375000
b1011 #
b1011 %
b1011 '
#380000
b1100 #
b1100 %
b1100 '
#385000
b1101 #
b1101 %
b1101 '
#390000
b1110 #
b1110 %
b1110 '
#395000
b1111 #
b1111 %
b1111 '
#400000
b0 #
b0 %
b101 "
b101 $
b101 &
b0 '
#405000
b1 #
b1 %
b1 '
#410000
b10 #
b10 %
b10 '
#415000
b11 #
b11 %
b11 '
#420000
b100 #
b100 %
b100 '
#425000
1!
b101 #
b101 %
b101 '
#430000
0!
b110 #
b110 %
b110 '
#435000
b111 #
b111 %
b111 '
#440000
b1000 #
b1000 %
b1000 '
#445000
b1001 #
b1001 %
b1001 '
#450000
b1010 #
b1010 %
b1010 '
#455000
b1011 #
b1011 %
b1011 '
#460000
b1100 #
b1100 %
b1100 '
#465000
b1101 #
b1101 %
b1101 '
#470000
b1110 #
b1110 %
b1110 '
#475000
b1111 #
b1111 %
b1111 '
#480000
b0 #
b0 %
b110 "
b110 $
b110 &
b0 '
#485000
b1 #
b1 %
b1 '
#490000
b10 #
b10 %
b10 '
#495000
b11 #
b11 %
b11 '
#500000
b100 #
b100 %
b100 '
#505000
b101 #
b101 %
b101 '
#510000
1!
b110 #
b110 %
b110 '
#515000
0!
b111 #
b111 %
b111 '
#520000
b1000 #
b1000 %
b1000 '
#525000
b1001 #
b1001 %
b1001 '
#530000
b1010 #
b1010 %
b1010 '
#535000
b1011 #
b1011 %
b1011 '
#540000
b1100 #
b1100 %
b1100 '
#545000
b1101 #
b1101 %
b1101 '
#550000
b1110 #
b1110 %
b1110 '
#555000
b1111 #
b1111 %
b1111 '
#560000
b0 #
b0 %
b111 "
b111 $
b111 &
b0 '
#565000
b1 #
b1 %
b1 '
#570000
b10 #
b10 %
b10 '
#575000
b11 #
b11 %
b11 '
#580000
b100 #
b100 %
b100 '
#585000
b101 #
b101 %
b101 '
#590000
b110 #
b110 %
b110 '
#595000
1!
b111 #
b111 %
b111 '
#600000
0!
b1000 #
b1000 %
b1000 '
#605000
b1001 #
b1001 %
b1001 '
#610000
b1010 #
b1010 %
b1010 '
#615000
b1011 #
b1011 %
b1011 '
#620000
b1100 #
b1100 %
b1100 '
#625000
b1101 #
b1101 %
b1101 '
#630000
b1110 #
b1110 %
b1110 '
#635000
b1111 #
b1111 %
b1111 '
#640000
b0 #
b0 %
b1000 "
b1000 $
b1000 &
b0 '
#645000
b1 #
b1 %
b1 '
#650000
b10 #
b10 %
b10 '
#655000
b11 #
b11 %
b11 '
#660000
b100 #
b100 %
b100 '
#665000
b101 #
b101 %
b101 '
#670000
b110 #
b110 %
b110 '
#675000
b111 #
b111 %
b111 '
#680000
1!
b1000 #
b1000 %
b1000 '
#685000
0!
b1001 #
b1001 %
b1001 '
#690000
b1010 #
b1010 %
b1010 '
#695000
b1011 #
b1011 %
b1011 '
#700000
b1100 #
b1100 %
b1100 '
#705000
b1101 #
b1101 %
b1101 '
#710000
b1110 #
b1110 %
b1110 '
#715000
b1111 #
b1111 %
b1111 '
#720000
b0 #
b0 %
b1001 "
b1001 $
b1001 &
b0 '
#725000
b1 #
b1 %
b1 '
#730000
b10 #
b10 %
b10 '
#735000
b11 #
b11 %
b11 '
#740000
b100 #
b100 %
b100 '
#745000
b101 #
b101 %
b101 '
#750000
b110 #
b110 %
b110 '
#755000
b111 #
b111 %
b111 '
#760000
b1000 #
b1000 %
b1000 '
#765000
1!
b1001 #
b1001 %
b1001 '
#770000
0!
b1010 #
b1010 %
b1010 '
#775000
b1011 #
b1011 %
b1011 '
#780000
b1100 #
b1100 %
b1100 '
#785000
b1101 #
b1101 %
b1101 '
#790000
b1110 #
b1110 %
b1110 '
#795000
b1111 #
b1111 %
b1111 '
#800000
b0 #
b0 %
b1010 "
b1010 $
b1010 &
b0 '
#805000
b1 #
b1 %
b1 '
#810000
b10 #
b10 %
b10 '
#815000
b11 #
b11 %
b11 '
#820000
b100 #
b100 %
b100 '
#825000
b101 #
b101 %
b101 '
#830000
b110 #
b110 %
b110 '
#835000
b111 #
b111 %
b111 '
#840000
b1000 #
b1000 %
b1000 '
#845000
b1001 #
b1001 %
b1001 '
#850000
1!
b1010 #
b1010 %
b1010 '
#855000
0!
b1011 #
b1011 %
b1011 '
#860000
b1100 #
b1100 %
b1100 '
#865000
b1101 #
b1101 %
b1101 '
#870000
b1110 #
b1110 %
b1110 '
#875000
b1111 #
b1111 %
b1111 '
#880000
b0 #
b0 %
b1011 "
b1011 $
b1011 &
b0 '
#885000
b1 #
b1 %
b1 '
#890000
b10 #
b10 %
b10 '
#895000
b11 #
b11 %
b11 '
#900000
b100 #
b100 %
b100 '
#905000
b101 #
b101 %
b101 '
#910000
b110 #
b110 %
b110 '
#915000
b111 #
b111 %
b111 '
#920000
b1000 #
b1000 %
b1000 '
#925000
b1001 #
b1001 %
b1001 '
#930000
b1010 #
b1010 %
b1010 '
#935000
1!
b1011 #
b1011 %
b1011 '
#940000
0!
b1100 #
b1100 %
b1100 '
#945000
b1101 #
b1101 %
b1101 '
#950000
b1110 #
b1110 %
b1110 '
#955000
b1111 #
b1111 %
b1111 '
#960000
b0 #
b0 %
b1100 "
b1100 $
b1100 &
b0 '
#965000
b1 #
b1 %
b1 '
#970000
b10 #
b10 %
b10 '
#975000
b11 #
b11 %
b11 '
#980000
b100 #
b100 %
b100 '
#985000
b101 #
b101 %
b101 '
#990000
b110 #
b110 %
b110 '
#995000
b111 #
b111 %
b111 '
#1000000
b1000 #
b1000 %
b1000 '
#1005000
b1001 #
b1001 %
b1001 '
#1010000
b1010 #
b1010 %
b1010 '
#1015000
b1011 #
b1011 %
b1011 '
#1020000
1!
b1100 #
b1100 %
b1100 '
#1025000
0!
b1101 #
b1101 %
b1101 '
#1030000
b1110 #
b1110 %
b1110 '
#1035000
b1111 #
b1111 %
b1111 '
#1040000
b0 #
b0 %
b1101 "
b1101 $
b1101 &
b0 '
#1045000
b1 #
b1 %
b1 '
#1050000
b10 #
b10 %
b10 '
#1055000
b11 #
b11 %
b11 '
#1060000
b100 #
b100 %
b100 '
#1065000
b101 #
b101 %
b101 '
#1070000
b110 #
b110 %
b110 '
#1075000
b111 #
b111 %
b111 '
#1080000
b1000 #
b1000 %
b1000 '
#1085000
b1001 #
b1001 %
b1001 '
#1090000
b1010 #
b1010 %
b1010 '
#1095000
b1011 #
b1011 %
b1011 '
#1100000
b1100 #
b1100 %
b1100 '
#1105000
1!
b1101 #
b1101 %
b1101 '
#1110000
0!
b1110 #
b1110 %
b1110 '
#1115000
b1111 #
b1111 %
b1111 '
#1120000
b0 #
b0 %
b1110 "
b1110 $
b1110 &
b0 '
#1125000
b1 #
b1 %
b1 '
#1130000
b10 #
b10 %
b10 '
#1135000
b11 #
b11 %
b11 '
#1140000
b100 #
b100 %
b100 '
#1145000
b101 #
b101 %
b101 '
#1150000
b110 #
b110 %
b110 '
#1155000
b111 #
b111 %
b111 '
#1160000
b1000 #
b1000 %
b1000 '
#1165000
b1001 #
b1001 %
b1001 '
#1170000
b1010 #
b1010 %
b1010 '
#1175000
b1011 #
b1011 %
b1011 '
#1180000
b1100 #
b1100 %
b1100 '
#1185000
b1101 #
b1101 %
b1101 '
#1190000
1!
b1110 #
b1110 %
b1110 '
#1195000
0!
b1111 #
b1111 %
b1111 '
#1200000
b0 #
b0 %
0!
b1111 "
b1111 $
b1111 &
b0 '
#1205000
b1 #
b1 %
b1 '
#1210000
b10 #
b10 %
b10 '
#1215000
b11 #
b11 %
b11 '
#1220000
b100 #
b100 %
b100 '
#1225000
b101 #
b101 %
b101 '
#1230000
b110 #
b110 %
b110 '
#1235000
b111 #
b111 %
b111 '
#1240000
b1000 #
b1000 %
b1000 '
#1245000
b1001 #
b1001 %
b1001 '
#1250000
b1010 #
b1010 %
b1010 '
#1255000
b1011 #
b1011 %
b1011 '
#1260000
b1100 #
b1100 %
b1100 '
#1265000
b1101 #
b1101 %
b1101 '
#1270000
b1110 #
b1110 %
b1110 '
#1275000
1!
b1111 #
b1111 %
b1111 '
#1280000
b10000 &
b10000 '
